Metadata-Version: 1.1
Name: clt-spacy
Version: 0.1
Summary: Helper module for Cloud Language Tools, install spacy and language packages
Home-page: https://github.com/Language-Tools/cloud-language-tools-core
Author: Luc
Author-email: languagetools@mailc.net
License: GPL
Platform: UNKNOWN
Classifier: Programming Language :: Python :: 3.7
Classifier: Programming Language :: Python :: 3.8
Classifier: Topic :: Text Processing :: Linguistic
